serper_wrapper/__init__.py
serper_wrapper/client.py
serper_wrapper/cache/__init__.py
serper_wrapper/cache/base.py
serper_wrapper/cache/disk_cache.py
serper_wrapper/cache/mongo_cache.py
serper_wrapper/exceptions/__init__.py
serper_wrapper/exceptions/exceptions.py
serper_wrapper-0.1.0.dist-info/METADATA
serper_wrapper-0.1.0.dist-info/WHEEL
serper_wrapper-0.1.0.dist-info/top_level.txt
serper_wrapper-0.1.0.dist-info/RECORD
