Metadata-Version: 2.4
Name: serper-wrapper
Version: 0.1.0
Summary: Python package for calling Serper API with support for disk and MongoDB caching
Home-page: https://github.com/yourusername/serper-wrapper
Author: Serper Wrapper
Author-email: your.email@example.com
Classifier: Programming Language :: Python :: 3
Classifier: Programming Language :: Python :: 3.7
Classifier: Programming Language :: Python :: 3.8
Classifier: Programming Language :: Python :: 3.9
Classifier: Programming Language :: Python :: 3.10
Classifier: License :: OSI Approved :: MIT License
Classifier: Operating System :: OS Independent
Requires-Python: >=3.7
Requires-Dist: requests>=2.25.0
Requires-Dist: pymongo>=3.11.0
Requires-Dist: prometheus_client>=0.12.0
Provides-Extra: mongo
Requires-Dist: pymongo>=3.11.0; extra == "mongo"
Provides-Extra: metrics
Requires-Dist: prometheus_client>=0.12.0; extra == "metrics"
Provides-Extra: all
Requires-Dist: pymongo>=3.11.0; extra == "all"
Requires-Dist: prometheus_client>=0.12.0; extra == "all"
Dynamic: author
Dynamic: author-email
Dynamic: classifier
Dynamic: description
Dynamic: description-content-type
Dynamic: home-page
Dynamic: provides-extra
Dynamic: requires-dist
Dynamic: requires-python
Dynamic: summary
